Funz/__init__.py
Funz/calculator.py
Funz/client.py
Funz/install.py
Funz/inst/Funz/Funz.R
Funz/inst/Funz/Funz.bat
Funz/inst/Funz/Funz.conf
Funz/inst/Funz/Funz.profile
Funz/inst/Funz/Funz.py
Funz/inst/Funz/Funz.sh
Funz/inst/Funz/FunzDaemon.bat
Funz/inst/Funz/FunzDaemon.sh
Funz/inst/Funz/FunzDaemon_start.sh
Funz/inst/Funz/FunzDaemon_stop.sh
Funz/inst/Funz/FunzDaemon_won.sh
Funz/inst/Funz/calculator.xml
Funz/inst/Funz/quotas.hex
Funz/inst/Funz/__pycache__/Funz.cpython-312.pyc
Funz/inst/Funz/lib/REngine-2.1.0.jar
Funz/inst/Funz/lib/Rserve-1.8.1.jar
Funz/inst/Funz/lib/Rsession-3.1.8.jar
Funz/inst/Funz/lib/commons-exec-1.1.jar
Funz/inst/Funz/lib/commons-io-2.4.jar
Funz/inst/Funz/lib/commons-lang-2.6.jar
Funz/inst/Funz/lib/commons.LICENSE.txt
Funz/inst/Funz/lib/ftplet-api-1.1.1.jar
Funz/inst/Funz/lib/ftpserver-core-1.1.1.jar
Funz/inst/Funz/lib/funz-calculator-1.16.jar
Funz/inst/Funz/lib/funz-client-1.16.jar
Funz/inst/Funz/lib/funz-core-1.16.jar
Funz/inst/Funz/lib/jmatharray.jar
Funz/inst/Funz/lib/jmathio.jar
Funz/inst/Funz/lib/jsonpath-2.1.jar
Funz/inst/Funz/lib/mina-core-2.0.16.jar
Funz/inst/Funz/lib/opencsv-2.3.jar
Funz/inst/Funz/lib/renjin-jar-with-dependencies.jar
Funz/inst/Funz/lib/sigar-1.6.6.jar
Funz/inst/Funz/lib/slf4j-api-1.7.2.jar
Funz/inst/Funz/lib/slf4j-nop-1.7.2.jar
Funz/inst/Funz/plugins/io/Python.ioplugin
Funz/inst/Funz/samples/branin.py
Funz/inst/Funz/scripts/Python.bat
Funz/inst/Funz/scripts/Python.sh
Funz/inst/Funz/scripts/oar.sh
Funz/inst/Funz/scripts/sge.sh
Funz/inst/Funz/scripts/slurm.sh
Funz-1.16.post1.data/scripts/Funz.py
Funz-1.16.post1.data/scripts/calculator.py
Funz-1.16.post1.data/scripts/client.py
Funz-1.16.post1.data/scripts/install.py
Funz-1.16.post1.dist-info/METADATA
Funz-1.16.post1.dist-info/WHEEL
Funz-1.16.post1.dist-info/top_level.txt
Funz-1.16.post1.dist-info/RECORD
