Metadata-Version: 2.1
Name: Funz
Version: 1.16.post1
Summary: Parametric Computing Environment
Home-page: https://github.com/Funz/Funz.py
Author: Yann Richet
Author-email: yann.richet@irsn.fr
Classifier: Programming Language :: Python :: 3
Classifier: License :: OSI Approved :: Apache Software License
Classifier: Operating System :: OS Independent
Requires-Dist: numpy
Requires-Dist: py4j
Requires-Dist: requests
